pytest_clerk_mock/__init__.py
pytest_clerk_mock/client.py
pytest_clerk_mock/helpers.py
pytest_clerk_mock/models/__init__.py
pytest_clerk_mock/models/auth.py
pytest_clerk_mock/models/organization.py
pytest_clerk_mock/models/user.py
pytest_clerk_mock/plugin.py
pytest_clerk_mock/services/__init__.py
pytest_clerk_mock/services/auth.py
pytest_clerk_mock/services/organization_memberships.py
pytest_clerk_mock/services/organizations.py
pytest_clerk_mock/services/users.py
pytest_clerk_mock-0.1.0.dist-info/LICENSE
pytest_clerk_mock-0.1.0.dist-info/METADATA
pytest_clerk_mock-0.1.0.dist-info/WHEEL
pytest_clerk_mock-0.1.0.dist-info/entry_points.txt
pytest_clerk_mock-0.1.0.dist-info/RECORD
