Metadata-Version: 2.3
Name: pytest-clerk-mock
Version: 0.1.0
Summary: A pytest plugin for mocking Clerk authentication
Author: Julien Kmec
Author-email: me@julien.dev
Requires-Python: >=3.11
Classifier: Programming Language :: Python :: 3
Classifier: Programming Language :: Python :: 3.11
Classifier: Programming Language :: Python :: 3.12
Classifier: Programming Language :: Python :: 3.13
Requires-Dist: clerk-backend-api (>=1.0.0)
Requires-Dist: pydantic (>=2.0.0)
Project-URL: Repository, https://github.com/julien777z/pytest-mock-clerk
